{
	"info": {
		"_postman_id": "9faa9b4c-be58-4924-b1b8-07588d46b44b",
		"name": "Shows",
		"schema": "https://schema.getpostman.com/json/collection/v2.1.0/collection.json",
		"_exporter_id": "17535481"
	},
	"item": [
		{
			"name": "Add a show",
			"event": [
				{
					"listen": "test",
					"script": {
						"exec": [
							"var data = pm.response.json()",
							"pm.globals.set(\"show_id\", data.id);",
							"",
							"pm.test(\"Status code is 201\", function () {",
							"   pm.response.to.have.status(201);",
							"});"
						],
						"type": "text/javascript"
					}
				}
			],
			"request": {
				"auth": {
					"type": "bearer",
					"bearer": [
						{
							"key": "token",
							"value": "{{api_user_id}}",
							"type": "string"
						}
					]
				},
				"method": "POST",
				"header": [],
				"body": {
					"mode": "raw",
					"raw": "{\n    \"name\": \"Jujutsu Kaisen\",\n    \"poster\": \"https://m.media-amazon.com/images/M/MV5BMTMwMDM4N2EtOTJiYy00OTQ0LThlZDYtYWUwOWFlY2IxZGVjXkEyXkFqcGdeQXVyNjAwNDUxODI@._V1_FMjpg_UX1000_.jpg\"\n}",
					"options": {
						"raw": {
							"language": "json"
						}
					}
				},
				"url": {
					"raw": "{{baseUrl}}/shows",
					"host": [
						"{{baseUrl}}"
					],
					"path": [
						"shows"
					]
				}
			},
			"response": [
				{
					"name": "Add a show",
					"originalRequest": {
						"method": "POST",
						"header": [],
						"body": {
							"mode": "raw",
							"raw": "{\n    \"name\": \"Jujutsu Kaisen\",\n    \"poster\": \"https://m.media-amazon.com/images/M/MV5BMTMwMDM4N2EtOTJiYy00OTQ0LThlZDYtYWUwOWFlY2IxZGVjXkEyXkFqcGdeQXVyNjAwNDUxODI@._V1_FMjpg_UX1000_.jpg\"\n}",
							"options": {
								"raw": {
									"language": "json"
								}
							}
						},
						"url": {
							"raw": "{{baseUrl}}/shows",
							"host": [
								"{{baseUrl}}"
							],
							"path": [
								"shows"
							]
						}
					},
					"status": "Created",
					"code": 201,
					"_postman_previewlanguage": "json",
					"header": [
						{
							"key": "Content-Type",
							"value": "application/json",
							"name": "Content-Type",
							"description": "",
							"type": "text"
						}
					],
					"cookie": [],
					"body": "{   \n    \"id\": \"270b923c-4db5-47b5-8cc5-d90e431217c9\",\n    \"name\": \"Jujutsu Kaisen\",\n    \"poster\": \"https://m.media-amazon.com/images/M/MV5BMTMwMDM4N2EtOTJiYy00OTQ0LThlZDYtYWUwOWFlY2IxZGVjXkEyXkFqcGdeQXVyNjAwNDUxODI@._V1_FMjpg_UX1000_.jpg\"   \n}"
				}
			]
		},
		{
			"name": "Get all shows",
			"event": [
				{
					"listen": "test",
					"script": {
						"exec": [
							"pm.test('Number of shows > ' + 0, function () {",
							"    var data = pm.response.json()",
							"    pm.expect(data.length).to.greaterThan(0)",
							"});",
							"",
							"pm.test(\"Status code is 200\", function () {",
							"    pm.response.to.have.status(200);",
							"});"
						],
						"type": "text/javascript"
					}
				}
			],
			"request": {
				"auth": {
					"type": "bearer",
					"bearer": [
						{
							"key": "token",
							"value": "{{api_user_id}}",
							"type": "string"
						}
					]
				},
				"method": "GET",
				"header": [],
				"url": {
					"raw": "{{baseUrl}}/shows",
					"host": [
						"{{baseUrl}}"
					],
					"path": [
						"shows"
					]
				}
			},
			"response": [
				{
					"name": "Get all shows",
					"originalRequest": {
						"method": "GET",
						"header": [],
						"url": {
							"raw": "{{baseUrl}}/shows",
							"host": [
								"{{baseUrl}}"
							],
							"path": [
								"shows"
							]
						}
					},
					"status": "OK",
					"code": 200,
					"_postman_previewlanguage": "json",
					"header": [
						{
							"key": "Content-Type",
							"value": "application/json",
							"name": "Content-Type",
							"description": "",
							"type": "text"
						}
					],
					"cookie": [],
					"body": "[\n    {\n        \"id\": \"6237d8e6-d1f7-486c-9963-7e24d992fa61\",\n        \"name\": \"Jujutsu Kaisen\",\n        \"poster\": \"https://m.media-amazon.com/images/M/MV5BMTMwMDM4N2EtOTJiYy00OTQ0LThlZDYtYWUwOWFlY2IxZGVjXkEyXkFqcGdeQXVyNjAwNDUxODI@._V1_FMjpg_UX1000_.jpg\",\n        \"genres\": [],\n        \"watching\": []\n    \n    },\n    {\n        \"id\": \"4286e256-8407-11ee-b962-0242ac120002\",\n        \"name\": \"Attack on Titan\",\n        \"poster\": \"https://m.media-amazon.com/images/M/MV5BNDFjYTIxMjctYTQ2ZC00OGQ4LWE3OGYtNDdiMzNiNDZlMDAwXkEyXkFqcGdeQXVyNzI3NjY3NjQ@._V1_FMjpg_UX1000_.jpg\",\n        \"genres\": [],\n        \"watching\": []\n    \n    }\n]"
				}
			]
		},
		{
			"name": "Get one show",
			"event": [
				{
					"listen": "test",
					"script": {
						"exec": [
							"pm.test(\"Status code is 200\", function () {",
							"    pm.response.to.have.status(200);",
							"});"
						],
						"type": "text/javascript"
					}
				}
			],
			"request": {
				"auth": {
					"type": "bearer",
					"bearer": [
						{
							"key": "token",
							"value": "{{api_user_id}}",
							"type": "string"
						}
					]
				},
				"method": "GET",
				"header": [],
				"url": {
					"raw": "{{baseUrl}}/shows/{{show_id}}",
					"host": [
						"{{baseUrl}}"
					],
					"path": [
						"shows",
						"{{show_id}}"
					]
				}
			},
			"response": [
				{
					"name": "Get one show",
					"originalRequest": {
						"method": "GET",
						"header": [],
						"url": {
							"raw": "{{baseUrl}}/shows/{{show_id}}",
							"host": [
								"{{baseUrl}}"
							],
							"path": [
								"shows",
								"{{show_id}}"
							]
						}
					},
					"status": "OK",
					"code": 200,
					"_postman_previewlanguage": "json",
					"header": [
						{
							"key": "Content-Type",
							"value": "application/json",
							"name": "Content-Type",
							"description": "",
							"type": "text"
						}
					],
					"cookie": [],
					"body": "{\n    \"id\": \"e86e313c-b51e-45ac-a154-41583b0c3e03\",\n    \"name\": \"Jujutsu Kaisen\",\n    \"poster\": \"https://m.media-amazon.com/images/M/MV5BMTMwMDM4N2EtOTJiYy00OTQ0LThlZDYtYWUwOWFlY2IxZGVjXkEyXkFqcGdeQXVyNjAwNDUxODI@._V1_FMjpg_UX1000_.jpg\",\n    \"watching\": [],\n    \"genres\": []\n}"
				}
			]
		},
		{
			"name": "Get an invalid show",
			"event": [
				{
					"listen": "test",
					"script": {
						"exec": [
							"pm.test(\"Status code is 404\", function () {",
							"   pm.response.to.have.status(404);",
							"});",
							"",
							"pm.test(\"Get expected error message\", function () {",
							"   var data = pm.response.json();",
							"   pm.expect(data.message).to.eql(\"The show with the given id was not found\");",
							"});"
						],
						"type": "text/javascript"
					}
				}
			],
			"request": {
				"auth": {
					"type": "bearer",
					"bearer": [
						{
							"key": "token",
							"value": "{{api_user_id}}",
							"type": "string"
						}
					]
				},
				"method": "GET",
				"header": [],
				"url": {
					"raw": "{{baseUrl}}/shows/{{invalid_id}}",
					"host": [
						"{{baseUrl}}"
					],
					"path": [
						"shows",
						"{{invalid_id}}"
					]
				}
			},
			"response": [
				{
					"name": "Get an invalid show",
					"originalRequest": {
						"method": "GET",
						"header": [],
						"url": {
							"raw": "{{baseUrl}}/shows/{{invalid_id}}",
							"host": [
								"{{baseUrl}}"
							],
							"path": [
								"shows",
								"{{invalid_id}}"
							]
						}
					},
					"status": "Not Found",
					"code": 404,
					"_postman_previewlanguage": "json",
					"header": [
						{
							"key": "Content-Type",
							"value": "application/json",
							"name": "Content-Type",
							"description": "",
							"type": "text"
						}
					],
					"cookie": [],
					"body": "{\n    \"statusCode\": 404,\n    \"message\": \"The show with the given id was not found\"\n}"
				}
			]
		},
		{
			"name": "Update a show",
			"event": [
				{
					"listen": "test",
					"script": {
						"exec": [
							"pm.test(\"Status code is 200\", function () {",
							"    pm.response.to.have.status(200);",
							"});"
						],
						"type": "text/javascript"
					}
				}
			],
			"request": {
				"auth": {
					"type": "bearer",
					"bearer": [
						{
							"key": "token",
							"value": "{{api_user_id}}",
							"type": "string"
						}
					]
				},
				"method": "PUT",
				"header": [],
				"body": {
					"mode": "raw",
					"raw": "{\n    \"name\": \"JJK\",\n    \"poster\": \"https://m.media-amazon.com/images/M/MV5BMTMwMDM4N2EtOTJiYy00OTQ0LThlZDYtYWUwOWFlY2IxZGVjXkEyXkFqcGdeQXVyNjAwNDUxODI@._V1_FMjpg_UX1000_.jpg\"\n}",
					"options": {
						"raw": {
							"language": "json"
						}
					}
				},
				"url": {
					"raw": "{{baseUrl}}/shows/{{show_id}}",
					"host": [
						"{{baseUrl}}"
					],
					"path": [
						"shows",
						"{{show_id}}"
					]
				}
			},
			"response": [
				{
					"name": "Update a show",
					"originalRequest": {
						"method": "PUT",
						"header": [],
						"body": {
							"mode": "raw",
							"raw": "{\n    \"name\": \"JJK\",\n    \"poster\": \"https://m.media-amazon.com/images/M/MV5BMTMwMDM4N2EtOTJiYy00OTQ0LThlZDYtYWUwOWFlY2IxZGVjXkEyXkFqcGdeQXVyNjAwNDUxODI@._V1_FMjpg_UX1000_.jpg\"\n}",
							"options": {
								"raw": {
									"language": "json"
								}
							}
						},
						"url": {
							"raw": "{{baseUrl}}/shows/{{show_id}}",
							"host": [
								"{{baseUrl}}"
							],
							"path": [
								"shows",
								"{{show_id}}"
							]
						}
					},
					"status": "OK",
					"code": 200,
					"_postman_previewlanguage": "json",
					"header": [
						{
							"key": "Content-Type",
							"value": "application/json",
							"name": "Content-Type",
							"description": "",
							"type": "text"
						}
					],
					"cookie": [],
					"body": "{\n    \"id\": \"ed597572-506e-4316-ad6a-7d406632714a\",\n    \"name\": \"JJK\",\n    \"poster\": \"https://m.media-amazon.com/images/M/MV5BMTMwMDM4N2EtOTJiYy00OTQ0LThlZDYtYWUwOWFlY2IxZGVjXkEyXkFqcGdeQXVyNjAwNDUxODI@._V1_FMjpg_UX1000_.jpg\"\n}"
				}
			]
		},
		{
			"name": "Update an invalid show",
			"event": [
				{
					"listen": "test",
					"script": {
						"exec": [
							"pm.test(\"Status code is 404\", function () {",
							"    pm.response.to.have.status(404);",
							"});",
							"",
							"pm.test(\"Get expected error message\", function () {",
							"    var data = pm.response.json();",
							"    pm.expect(data.message).to.eql(\"The show with the given id was not found\");",
							"});"
						],
						"type": "text/javascript"
					}
				}
			],
			"request": {
				"auth": {
					"type": "bearer",
					"bearer": [
						{
							"key": "token",
							"value": "{{api_user_id}}",
							"type": "string"
						}
					]
				},
				"method": "PUT",
				"header": [],
				"body": {
					"mode": "raw",
					"raw": "{\n    \"name\": \"JJK\",\n    \"poster\": \"https://m.media-amazon.com/images/M/MV5BMTMwMDM4N2EtOTJiYy00OTQ0LThlZDYtYWUwOWFlY2IxZGVjXkEyXkFqcGdeQXVyNjAwNDUxODI@._V1_FMjpg_UX1000_.jpg\"\n}",
					"options": {
						"raw": {
							"language": "json"
						}
					}
				},
				"url": {
					"raw": "{{baseUrl}}/shows/{{invalid_id}}",
					"host": [
						"{{baseUrl}}"
					],
					"path": [
						"shows",
						"{{invalid_id}}"
					]
				}
			},
			"response": [
				{
					"name": "Update an invalid show",
					"originalRequest": {
						"method": "PUT",
						"header": [],
						"body": {
							"mode": "raw",
							"raw": "{\n    \"name\": \"JJK\",\n    \"poster\": \"https://m.media-amazon.com/images/M/MV5BMTMwMDM4N2EtOTJiYy00OTQ0LThlZDYtYWUwOWFlY2IxZGVjXkEyXkFqcGdeQXVyNjAwNDUxODI@._V1_FMjpg_UX1000_.jpg\"\n}",
							"options": {
								"raw": {
									"language": "json"
								}
							}
						},
						"url": {
							"raw": "{{baseUrl}}/shows/{{invalid_id}}",
							"host": [
								"{{baseUrl}}"
							],
							"path": [
								"shows",
								"{{invalid_id}}"
							]
						}
					},
					"status": "Not Found",
					"code": 404,
					"_postman_previewlanguage": "json",
					"header": [
						{
							"key": "Content-Type",
							"value": "application/json",
							"name": "Content-Type",
							"description": "",
							"type": "text"
						}
					],
					"cookie": [],
					"body": "{\n    \"statusCode\": 404,\n    \"message\": \"The show with the given id was not found\"\n}"
				}
			]
		},
		{
			"name": "Delete a show",
			"event": [
				{
					"listen": "test",
					"script": {
						"exec": [
							"pm.test(\"Status code is 204\", function () {",
							"   pm.response.to.have.status(204);",
							"});"
						],
						"type": "text/javascript"
					}
				}
			],
			"request": {
				"auth": {
					"type": "bearer",
					"bearer": [
						{
							"key": "token",
							"value": "{{api_user_id}}",
							"type": "string"
						}
					]
				},
				"method": "DELETE",
				"header": [],
				"url": {
					"raw": "{{baseUrl}}/shows/{{show_id}}",
					"host": [
						"{{baseUrl}}"
					],
					"path": [
						"shows",
						"{{show_id}}"
					]
				}
			},
			"response": [
				{
					"name": "Delete a show",
					"originalRequest": {
						"method": "DELETE",
						"header": [],
						"url": {
							"raw": "{{baseUrl}}/shows/{{show_id}}",
							"host": [
								"{{baseUrl}}"
							],
							"path": [
								"shows",
								"{{show_id}}"
							]
						}
					},
					"status": "No Content",
					"code": 204,
					"_postman_previewlanguage": null,
					"header": null,
					"cookie": [],
					"body": null
				}
			]
		},
		{
			"name": "Delete an invalid show",
			"event": [
				{
					"listen": "test",
					"script": {
						"exec": [
							"pm.test(\"Status code is 404\", function () {",
							"    pm.response.to.have.status(404);",
							"});",
							"",
							"pm.test(\"Get expected error message\", function () {",
							"    var data = pm.response.json();",
							"    pm.expect(data.message).to.eql(\"The show with the given id was not found\");",
							"});"
						],
						"type": "text/javascript"
					}
				}
			],
			"request": {
				"auth": {
					"type": "bearer",
					"bearer": [
						{
							"key": "token",
							"value": "{{api_user_id}}",
							"type": "string"
						}
					]
				},
				"method": "DELETE",
				"header": [],
				"url": {
					"raw": "{{baseUrl}}/shows/{{invalid_id}}",
					"host": [
						"{{baseUrl}}"
					],
					"path": [
						"shows",
						"{{invalid_id}}"
					]
				}
			},
			"response": [
				{
					"name": "Delete an invalid show",
					"originalRequest": {
						"method": "DELETE",
						"header": [],
						"url": {
							"raw": "{{baseUrl}}/shows/{{invalid_id}}",
							"host": [
								"{{baseUrl}}"
							],
							"path": [
								"shows",
								"{{invalid_id}}"
							]
						}
					},
					"status": "Not Found",
					"code": 404,
					"_postman_previewlanguage": "json",
					"header": [
						{
							"key": "Content-Type",
							"value": "application/json",
							"name": "Content-Type",
							"description": "",
							"type": "text"
						}
					],
					"cookie": [],
					"body": "{\n    \"statusCode\": 404,\n    \"message\": \"The show with the given id was not found\"\n}"
				}
			]
		}
	],
	"event": [
		{
			"listen": "prerequest",
			"script": {
				"type": "text/javascript",
				"exec": [
					""
				]
			}
		},
		{
			"listen": "test",
			"script": {
				"type": "text/javascript",
				"exec": [
					""
				]
			}
		}
	],
	"variable": [
		{
			"key": "baseUrl",
			"value": "localhost:3000/api/v1",
			"type": "string"
		},
		{
			"key": "invalid_id",
			"value": "00000000-0000-0000-0000-000000000000",
			"type": "string"
		}
	]
}